{
  "shop": {
    "name": "blue-river-09b0c6103.5",
    "logo": "blob-stub/logo.png",
    "shortList": {
      "listType": "features",
      "title": "Топ продажів",
      "listId" : 2,
      "active": true
    },
    "weAre": "blue-river-09b0c6103.5 — це сучасний онлайн-магазин, що пропонує вишуканий вибір прикрас",
    "bio": "Ми прагнемо дарувати нашим клієнтам якість, стиль та комфорт у кожному виробі, підкреслюючи унікальність і особливість кожного. Від класичних речей до останніх трендів — знайдіть красу в деталях разом з нами!",
    "about": "Ласкаво просимо до blue-river-09b0c6103.5 — простору, де стиль і якість зливаються у досконалий тандем. Наша місія — створювати незабутній досвід покупок, пропонуючи лише найкращі колекції, що відповідають актуальним модним трендам і вашим вподобанням. Ми віримо, що кожна деталь має значення, тому ретельно відбираємо кожен товар, щоб забезпечити нашим клієнтам комфорт та впевненість у собі.<br><br>Наша команда прагне надихати на індивідуальність, допомагаючи вам віднайти власний стиль, що підкреслить вашу унікальність. blue-river-09b0c6103.5 — це не просто магазин, а місце, де кожен знаходить щось особливе.",
    "contacts": {
      "instagram": { "name": "blue-river-09b0c6103.5", "link": "https://www.instagram.com" },
      "mail": "mail@example.com",
      "facebook": { "name": "blue-river-09b0c6103.5", "link": "https://www.facebook.com/" },
      "phone": "+01234567891"
    }
  },
  "blobStorageUrl": "/blob-stub",
  "categoriesSrc": "/blob-stub/categories.json",
  "featuresSrc": "/blob-stub/features.json",
  "productsSrc": "/blob-stub/products.json",
  "packagingSrc": "/blob-stub/packaging.json",
  "createOrderUrl": "https://example.com",
  "specialOffersUrl": "/blob-stub/special-offers.json",
  "bannerUrl": "/blob-stub/banner.json"
}
